smdb_web_interface/__init__.py
smdb_web_interface/helpers.py
smdb_web_interface/static.py
smdb_web_interface/templates.py
smdb_web_interface-0.1.6.dist-info/licenses/LICENSE
smdb_web_interface-0.1.6.dist-info/METADATA
smdb_web_interface-0.1.6.dist-info/WHEEL
smdb_web_interface-0.1.6.dist-info/top_level.txt
smdb_web_interface-0.1.6.dist-info/RECORD
