Metadata-Version: 2.4
Name: smdb_web_interface
Version: 0.1.6
Summary: An easy to use Web interface for python application.
Home-page: https://github.com/NightKey/web-cli
Author: Janthó Dávid
Author-email: davidjantho@gmail.com
Project-URL: Bug Tracker, https://github.com/NightKey/web-cli/issues
Classifier: Development Status :: 4 - Beta
Classifier: Programming Language :: Python :: 3
Classifier: License :: Freeware
Classifier: Operating System :: OS Independent
Requires-Python: >=3.7
License-File: LICENSE
Dynamic: license-file
